huaweicloudsdkvpc/__init__.py
huaweicloudsdkvpc/v2/__init__.py
huaweicloudsdkvpc/v2/vpc_async_client.py
huaweicloudsdkvpc/v2/vpc_client.py
huaweicloudsdkvpc/v2/model/__init__.py
huaweicloudsdkvpc/v2/model/accept_vpc_peering_request.py
huaweicloudsdkvpc/v2/model/accept_vpc_peering_response.py
huaweicloudsdkvpc/v2/model/add_route_table_route.py
huaweicloudsdkvpc/v2/model/allocation_pool.py
huaweicloudsdkvpc/v2/model/allowed_address_pair.py
huaweicloudsdkvpc/v2/model/asscoiate_req.py
huaweicloudsdkvpc/v2/model/associate_route_table_and_subnet_req.py
huaweicloudsdkvpc/v2/model/associate_route_table_request.py
huaweicloudsdkvpc/v2/model/associate_route_table_response.py
huaweicloudsdkvpc/v2/model/batch_create_security_group_tags_request.py
huaweicloudsdkvpc/v2/model/batch_create_security_group_tags_request_body.py
huaweicloudsdkvpc/v2/model/batch_create_security_group_tags_response.py
huaweicloudsdkvpc/v2/model/batch_create_subnet_tags_request.py
huaweicloudsdkvpc/v2/model/batch_create_subnet_tags_request_body.py
huaweicloudsdkvpc/v2/model/batch_create_subnet_tags_response.py
huaweicloudsdkvpc/v2/model/batch_create_vpc_tags_request.py
huaweicloudsdkvpc/v2/model/batch_create_vpc_tags_request_body.py
huaweicloudsdkvpc/v2/model/batch_create_vpc_tags_response.py
huaweicloudsdkvpc/v2/model/batch_delete_security_group_tags_request.py
huaweicloudsdkvpc/v2/model/batch_delete_security_group_tags_request_body.py
huaweicloudsdkvpc/v2/model/batch_delete_security_group_tags_response.py
huaweicloudsdkvpc/v2/model/batch_delete_subnet_tags_request.py
huaweicloudsdkvpc/v2/model/batch_delete_subnet_tags_request_body.py
huaweicloudsdkvpc/v2/model/batch_delete_subnet_tags_response.py
huaweicloudsdkvpc/v2/model/batch_delete_vpc_tags_request.py
huaweicloudsdkvpc/v2/model/batch_delete_vpc_tags_request_body.py
huaweicloudsdkvpc/v2/model/batch_delete_vpc_tags_response.py
huaweicloudsdkvpc/v2/model/binding_vif_details.py
huaweicloudsdkvpc/v2/model/create_flow_log_req.py
huaweicloudsdkvpc-3.1.184.dist-info/METADATA
huaweicloudsdkvpc-3.1.184.dist-info/WHEEL
huaweicloudsdkvpc-3.1.184.dist-info/licenses/LICENSE
huaweicloudsdkvpc-3.1.184.dist-info/RECORD
